piqmp6988/__init__.py
piqmp6988/piqmp6988.py
piqmp6988-1.0.1.dist-info/DESCRIPTION.rst
piqmp6988-1.0.1.dist-info/METADATA
piqmp6988-1.0.1.dist-info/RECORD
piqmp6988-1.0.1.dist-info/WHEEL
piqmp6988-1.0.1.dist-info/metadata.json
piqmp6988-1.0.1.dist-info/top_level.txt
