Metadata-Version: 2.0
Name: piqmp6988
Version: 1.0.1
Summary: To use QMP6988 with pigpio.
Home-page: https://github.com/Langur/piqmp6988
Author: Akihisa ONODA
Author-email: akihisa.onoda@osarusystem.com
License: MIT
Keywords: piqmp6988 qmp6988 env3hat pigpio temperature pressure sensor i2c
Platform: UNKNOWN
Classifier: License :: OSI Approved :: MIT License
Classifier: Programming Language :: Python :: 3
Classifier: Programming Language :: Python :: 3.7
Requires-Dist: pigpio
